{
  "min": {
    "2": {
      "(7, (7,))": 222280,
      "(7, (1, 6))": 47206,
      "(8, (8,))": 200620,
      "(5, (5,))": 164622,
      "(7, (3, 4))": 30491,
      "(9, (9,))": 141537,
      "(2, (2,))": 38020,
      "(6, (6,))": 193276,
      "(10, (1, 9))": 88243,
      "(11, (3, 8))": 26259,
      "(7, (2, 5))": 35542,
      "(10, (4, 6))": 17624,
      "(8, (1, 7))": 36756,
      "(3, (3,))": 83165,
      "(3, (1, 2))": 9704,
      "(11, (4, 7))": 14039,
      "(4, (4,))": 126664,
      "(6, (1, 2, 3))": 2526,
      "(11, (2, 9))": 62277,
      "(9, (1, 8))": 35202,
      "(9, (3, 6))": 19890,
      "(10, (3, 7))": 21390,
      "(10, (1, 4, 5))": 3390,
      "(12, (3, 9))": 31434,
      "(9, (4, 5))": 17552,
      "(5, (2, 3))": 19297,
      "(12, (4, 8))": 13678,
      "(8, (2, 6))": 26596,
      "(6, (1, 5))": 36591,
      "(8, (3, 5))": 22209,
      "(4, (1, 3))": 15171,
      "(5, (1, 4))": 25274,
      "(8, (1, 3, 4))": 3614,
      "(9, (1, 2, 6))": 1240,
      "(10, (2, 8))": 36618,
      "(6, (2, 4))": 27899,
      "(11, (5, 6))": 10122,
      "(10, (1, 3, 6))": 1667,
      "(12, (1, 2, 9))": 860,
      "(9, (2, 7))": 26612,
      "(8, (1, 2, 5))": 1834,
      "(10, (2, 3, 5))": 3913,
      "(11, (1, 3, 7))": 1062,
      "(12, (3, 4, 5))": 1308,
      "(11, (2, 4, 5))": 2009,
      "(12, (5, 7))": 6916,
      "(11, (2, 3, 6))": 1117,
      "(9, (1, 3, 5))": 1384,
      "(12, (1, 5, 6))": 1558,
      "(11, (1, 4, 6))": 1285,
      "(9, (2, 3, 4))": 2309,
      "(12, (1, 4, 7))": 788,
      "(1, (1,))": 2606,
      "(12, (1, 3, 8))": 961,
      "(12, (2, 4, 6))": 1277,
      "(10, (1, 2, 7))": 1448,
      "(10, (1, 2, 3, 4))": 318,
      "(11, (1, 2, 8))": 1147,
      "(7, (1, 2, 4))": 2059,
      "(12, (2, 3, 7))": 912,
      "(12, (1, 2, 3, 6))": 82,
      "(11, (1, 2, 3, 5))": 237,
      "(12, (1, 2, 4, 5))": 164
    },
    "3": {
      "(10, (1, 9))": 101819,
      "(6, (6,))": 219392,
      "(7, (7,))": 254935,
      "(7, (2, 5))": 42399,
      "(7, (3, 4))": 38798,
      "(6, (1, 5))": 41629,
      "(11, (2, 9))": 73866,
      "(8, (8,))": 234220,
      "(9, (2, 7))": 32519,
      "(4, (4,))": 143316,
      "(9, (3, 6))": 25221,
      "(5, (5,))": 186912,
      "(2, (2,))": 41152,
      "(6, (2, 4))": 32960,
      "(3, (3,))": 92542,
      "(8, (2, 6))": 32469,
      "(7, (1, 6))": 54718,
      "(8, (3, 5))": 28818,
      "(12, (4, 8))": 16947,
      "(12, (3, 9))": 37761,
      "(11, (1, 4, 6))": 1756,
      "(11, (4, 7))": 17796,
      "(9, (9,))": 165983,
      "(5, (1, 4))": 28637,
      "(5, (2, 3))": 22555,
      "(10, (1, 2, 7))": 1944,
      "(9, (4, 5))": 23396,
      "(10, (4, 6))": 22153,
      "(8, (1, 7))": 42860,
      "(12, (5, 7))": 8574,
      "(10, (3, 7))": 26575,
      "(8, (1, 3, 4))": 4944,
      "(11, (3, 8))": 32611,
      "(11, (5, 6))": 12729,
      "(9, (1, 3, 5))": 2075,
      "(9, (2, 3, 4))": 3291,
      "(4, (1, 3))": 16686,
      "(3, (1, 2))": 10419,
      "(9, (1, 8))": 42816,
      "(9, (1, 2, 6))": 1862,
      "(10, (2, 8))": 43679,
      "(11, (2, 4, 5))": 2804,
      "(10, (2, 3, 5))": 5316,
      "(8, (1, 2, 5))": 2503,
      "(10, (1, 4, 5))": 4525,
      "(7, (1, 2, 4))": 2850,
      "(6, (1, 2, 3))": 3143,
      "(12, (2, 4, 6))": 1695,
      "(12, (1, 3, 8))": 1159,
      "(12, (1, 4, 7))": 989,
      "(11, (1, 2, 8))": 1527,
      "(11, (1, 3, 7))": 1447,
      "(1, (1,))": 4121,
      "(12, (2, 3, 7))": 1305,
      "(12, (3, 4, 5))": 1881,
      "(11, (2, 3, 6))": 1588,
      "(12, (1, 5, 6))": 2154,
      "(12, (1, 2, 9))": 1140,
      "(10, (1, 3, 6))": 2212,
      "(12, (1, 2, 3, 6))": 110,
      "(10, (1, 2, 3, 4))": 437,
      "(11, (1, 2, 3, 5))": 336,
      "(12, (1, 2, 4, 5))": 228
    },
    "4": {
      "(8, (8,))": 254068,
      "(5, (5,))": 200546,
      "(8, (1, 7))": 46738,
      "(5, (2, 3))": 24256,
      "(10, (4, 6))": 25548,
      "(9, (9,))": 181337,
      "(9, (1, 8))": 47459,
      "(6, (6,))": 235282,
      "(7, (7,))": 272725,
      "(10, (1, 9))": 109742,
      "(9, (2, 7))": 35788,
      "(9, (3, 6))": 28495,
      "(4, (4,))": 153599,
      "(7, (2, 5))": 46849,
      "(10, (2, 8))": 48302,
      "(3, (3,))": 96902,
      "(11, (2, 9))": 80310,
      "(7, (1, 6))": 58117,
      "(12, (3, 9))": 42005,
      "(10, (3, 7))": 30517,
      "(2, (2,))": 43072,
      "(8, (3, 5))": 32853,
      "(6, (2, 4))": 35712,
      "(4, (1, 3))": 17895,
      "(12, (4, 8))": 19282,
      "(7, (3, 4))": 44265,
      "(9, (2, 3, 4))": 4214,
      "(8, (2, 6))": 36678,
      "(10, (1, 3, 6))": 2526,
      "(10, (1, 4, 5))": 5675,
      "(9, (4, 5))": 27137,
      "(10, (1, 2, 3, 4))": 543,
      "(6, (1, 5))": 43835,
      "(11, (3, 8))": 36147,
      "(11, (4, 7))": 20287,
      "(12, (5, 7))": 9785,
      "(3, (1, 2))": 10793,
      "(5, (1, 4))": 30401,
      "(12, (1, 5, 6))": 2425,
      "(10, (2, 3, 5))": 6221,
      "(11, (5, 6))": 14912,
      "(8, (1, 2, 5))": 3129,
      "(11, (1, 2, 8))": 1820,
      "(9, (1, 2, 6))": 2281,
      "(6, (1, 2, 3))": 3451,
      "(8, (1, 3, 4))": 5862,
      "(12, (1, 4, 7))": 1173,
      "(1, (1,))": 5896,
      "(9, (1, 3, 5))": 2581,
      "(11, (2, 3, 6))": 1915,
      "(12, (2, 4, 6))": 1927,
      "(11, (1, 3, 7))": 1698,
      "(7, (1, 2, 4))": 3390,
      "(11, (2, 4, 5))": 3346,
      "(12, (3, 4, 5))": 2248,
      "(12, (1, 2, 9))": 1201,
      "(11, (1, 4, 6))": 2148,
      "(11, (1, 2, 3, 5))": 408,
      "(10, (1, 2, 7))": 2365,
      "(12, (2, 3, 7))": 1577,
      "(12, (1, 3, 8))": 1323,
      "(12, (1, 2, 4, 5))": 289,
      "(12, (1, 2, 3, 6))": 148
    }
  },
  "max": {
    "2": {
      "(11, (1, 2, 3, 5))": 25783,
      "(9, (9,))": 98038,
      "(10, (4, 6))": 21675,
      "(8, (8,))": 131793,
      "(7, (7,))": 142126,
      "(8, (1, 2, 5))": 56552,
      "(9, (3, 6))": 29212,
      "(12, (4, 8))": 9804,
      "(7, (1, 2, 4))": 65223,
      "(12, (1, 2, 3, 6))": 12176,
      "(4, (1, 3))": 29569,
      "(7, (2, 5))": 14898,
      "(8, (3, 5))": 33744,
      "(9, (1, 2, 6))": 45311,
      "(9, (4, 5))": 30367,
      "(3, (3,))": 21836,
      "(11, (4, 7))": 18750,
      "(6, (6,))": 115808,
      "(6, (1, 2, 3))": 52497,
      "(5, (5,))": 80598,
      "(5, (1, 4))": 40809,
      "(9, (2, 7))": 10208,
      "(11, (3, 8))": 23210,
      "(11, (2, 4, 5))": 2095,
      "(10, (1, 2, 3, 4))": 35925,
      "(4, (4,))": 46829,
      "(5, (2, 3))": 5112,
      "(11, (2, 9))": 1334,
      "(3, (1, 2))": 18658,
      "(10, (3, 7))": 31622,
      "(11, (5, 6))": 13312,
      "(12, (3, 4, 5))": 2691,
      "(7, (3, 4))": 31837,
      "(10, (2, 8))": 4043,
      "(12, (2, 3, 7))": 1697,
      "(12, (5, 7))": 8275,
      "(10, (2, 3, 5))": 5135,
      "(6, (2, 4))": 4774,
      "(11, (2, 3, 6))": 2942,
      "(2, (2,))": 10913,
      "(8, (2, 6))": 11827,
      "(8, (1, 3, 4))": 1278,
      "(12, (3, 9))": 10113,
      "(10, (1, 3, 6))": 818,
      "(7, (1, 6))": 1565,
      "(9, (1, 3, 5))": 1160,
      "(11, (1, 3, 7))": 564,
      "(6, (1, 5))": 1294,
      "(12, (2, 4, 6))": 1303,
      "(12, (1, 3, 8))": 295,
      "(8, (1, 7))": 55,
      "(11, (1, 4, 6))": 28,
      "(9, (1, 8))": 53,
      "(10, (1, 4, 5))": 40,
      "(12, (1, 4, 7))": 20,
      "(12, (1, 5, 6))": 2,
      "(10, (1, 9))": 4
    },
    "3": {
      "(12, (1, 2, 3, 6))": 14399,
      "(8, (8,))": 195709,
      "(11, (4, 7))": 27376,
      "(4, (1, 3))": 33262,
      "(8, (2, 6))": 13924,
      "(9, (9,))": 157295,
      "(5, (5,))": 108871,
      "(9, (1, 2, 6))": 54211,
      "(9, (4, 5))": 40624,
      "(7, (7,))": 200048,
      "(11, (3, 8))": 31337,
      "(7, (1, 2, 4))": 75731,
      "(12, (3, 9))": 14000,
      "(6, (6,))": 157453,
      "(5, (1, 4))": 47169,
      "(9, (2, 7))": 12302,
      "(9, (3, 6))": 36261,
      "(11, (2, 3, 6))": 3353,
      "(11, (1, 2, 3, 5))": 31504,
      "(6, (1, 2, 3))": 59717,
      "(4, (4,))": 60993,
      "(8, (1, 2, 5))": 67666,
      "(3, (3,))": 25204,
      "(12, (4, 8))": 14310,
      "(8, (3, 5))": 42332,
      "(12, (5, 7))": 13007,
      "(7, (3, 4))": 38660,
      "(11, (5, 6))": 20706,
      "(10, (2, 8))": 4915,
      "(10, (1, 2, 3, 4))": 42487,
      "(3, (1, 2))": 20443,
      "(10, (3, 7))": 40909,
      "(7, (2, 5))": 17280,
      "(6, (2, 4))": 5021,
      "(10, (4, 6))": 30604,
      "(11, (2, 4, 5))": 2442,
      "(2, (2,))": 11998,
      "(9, (1, 3, 5))": 1298,
      "(8, (1, 3, 4))": 1429,
      "(10, (2, 3, 5))": 5991,
      "(5, (2, 3))": 5355,
      "(12, (2, 3, 7))": 1960,
      "(7, (1, 6))": 1716,
      "(12, (3, 4, 5))": 3547,
      "(12, (2, 4, 6))": 1503,
      "(11, (2, 9))": 1754,
      "(6, (1, 5))": 1388,
      "(11, (1, 3, 7))": 682,
      "(10, (1, 3, 6))": 880,
      "(12, (1, 3, 8))": 341,
      "(8, (1, 7))": 74,
      "(9, (1, 8))": 78,
      "(12, (1, 4, 7))": 23,
      "(10, (1, 4, 5))": 46,
      "(11, (1, 4, 6))": 29,
      "(10, (1, 9))": 4,
      "(12, (1, 5, 6))": 1
    },
    "4": {
      "(8, (1, 2, 5))": 75153,
      "(6, (6,))": 194232,
      "(9, (9,))": 215175,
      "(7, (3, 4))": 42384,
      "(6, (1, 2, 3))": 65332,
      "(11, (4, 7))": 33841,
      "(5, (5,))": 132670,
      "(8, (8,))": 252766,
      "(5, (1, 4))": 52107,
      "(10, (2, 3, 5))": 6285,
      "(7, (7,))": 250961,
      "(4, (1, 3))": 36008,
      "(8, (2, 6))": 15305,
      "(11, (1, 2, 3, 5))": 35480,
      "(10, (1, 2, 3, 4))": 46563,
      "(11, (5, 6))": 26647,
      "(7, (1, 2, 4))": 83253,
      "(10, (3, 7))": 47118,
      "(10, (4, 6))": 37348,
      "(2, (2,))": 13019,
      "(4, (4,))": 72296,
      "(12, (1, 2, 3, 6))": 16104,
      "(12, (4, 8))": 17899,
      "(9, (3, 6))": 40960,
      "(9, (1, 2, 6))": 60653,
      "(8, (3, 5))": 47723,
      "(9, (4, 5))": 47721,
      "(11, (3, 8))": 36526,
      "(3, (1, 2))": 22134,
      "(7, (2, 5))": 19503,
      "(3, (3,))": 28665,
      "(12, (3, 9))": 17052,
      "(5, (2, 3))": 5860,
      "(12, (5, 7))": 16878,
      "(10, (1, 3, 6))": 956,
      "(9, (2, 7))": 13565,
      "(6, (2, 4))": 5399,
      "(12, (3, 4, 5))": 4029,
      "(10, (2, 8))": 5594,
      "(12, (2, 4, 6))": 1537,
      "(11, (2, 4, 5))": 2551,
      "(7, (1, 6))": 1886,
      "(12, (1, 3, 8))": 393,
      "(11, (2, 3, 6))": 3588,
      "(9, (1, 3, 5))": 1391,
      "(8, (1, 3, 4))": 1521,
      "(11, (2, 9))": 1958,
      "(12, (2, 3, 7))": 2226,
      "(6, (1, 5))": 1595,
      "(11, (1, 3, 7))": 757,
      "(9, (1, 8))": 77,
      "(10, (1, 4, 5))": 46,
      "(11, (1, 4, 6))": 31,
      "(8, (1, 7))": 66,
      "(12, (1, 4, 7))": 20,
      "(12, (1, 5, 6))": 1,
      "(10, (1, 9))": 4
    }
  },
  "safe": {
    "2": {
      "(8, (2, 6))": 62737,
      "(7, (3, 4))": 30062,
      "(7, (7,))": 148991,
      "(6, (1, 5))": 42312,
      "(11, (2, 3, 6))": 25614,
      "(8, (8,))": 153846,
      "(4, (4,))": 77522,
      "(7, (2, 5))": 73603,
      "(6, (6,))": 111050,
      "(11, (1, 3, 7))": 587,
      "(6, (2, 4))": 54080,
      "(5, (5,))": 74533,
      "(11, (3, 8))": 21901,
      "(9, (2, 3, 4))": 44548,
      "(9, (4, 5))": 27727,
      "(9, (9,))": 105711,
      "(8, (1, 7))": 27252,
      "(10, (2, 3, 5))": 38722,
      "(5, (1, 4))": 35164,
      "(5, (2, 3))": 42377,
      "(10, (4, 6))": 18597,
      "(12, (3, 9))": 9425,
      "(9, (1, 8))": 14487,
      "(12, (2, 3, 7))": 13169,
      "(4, (1, 3))": 15072,
      "(7, (1, 6))": 34599,
      "(11, (4, 7))": 17997,
      "(10, (3, 7))": 29792,
      "(10, (1, 9))": 62792,
      "(12, (5, 7))": 7895,
      "(8, (3, 5))": 23725,
      "(12, (3, 4, 5))": 2143,
      "(12, (4, 8))": 10322,
      "(3, (3,))": 38087,
      "(11, (2, 9))": 1178,
      "(2, (2,))": 10156,
      "(9, (3, 6))": 23856,
      "(3, (1, 2))": 1328,
      "(11, (5, 6))": 13428,
      "(9, (2, 7))": 7545,
      "(12, (1, 5, 6))": 1957,
      "(10, (2, 8))": 3018,
      "(11, (1, 4, 6))": 2391,
      "(11, (2, 4, 5))": 1084,
      "(12, (1, 4, 7))": 1193,
      "(1, (1,))": 1521,
      "(12, (2, 4, 6))": 725,
      "(12, (1, 3, 8))": 162,
      "(12, (1, 2, 9))": 85,
      "(11, (1, 2, 8))": 4
    },
    "3": {
      "(3, (3,))": 42253,
      "(10, (2, 8))": 3617,
      "(6, (6,))": 137264,
      "(7, (7,))": 192999,
      "(6, (1, 5))": 53736,
      "(4, (4,))": 89340,
      "(8, (2, 6))": 71185,
      "(12, (3, 4, 5))": 2413,
      "(8, (8,))": 208635,
      "(6, (2, 4))": 60342,
      "(9, (9,))": 148895,
      "(7, (2, 5))": 84053,
      "(5, (1, 4))": 43522,
      "(5, (2, 3))": 47054,
      "(5, (5,))": 91538,
      "(9, (4, 5))": 33937,
      "(10, (1, 9))": 89170,
      "(9, (3, 6))": 28642,
      "(8, (3, 5))": 27195,
      "(7, (3, 4))": 34871,
      "(2, (2,))": 10782,
      "(8, (1, 7))": 38458,
      "(11, (3, 8))": 27336,
      "(10, (2, 3, 5))": 44967,
      "(11, (1, 4, 6))": 3346,
      "(9, (2, 7))": 8465,
      "(9, (1, 8))": 22907,
      "(9, (2, 3, 4))": 51861,
      "(11, (5, 6))": 17764,
      "(10, (3, 7))": 35607,
      "(7, (1, 6))": 46838,
      "(12, (3, 9))": 11901,
      "(12, (1, 4, 7))": 1769,
      "(12, (4, 8))": 14283,
      "(12, (1, 5, 6))": 2822,
      "(11, (4, 7))": 23299,
      "(4, (1, 3))": 15991,
      "(12, (2, 3, 7))": 15594,
      "(10, (4, 6))": 22380,
      "(11, (2, 3, 6))": 29729,
      "(1, (1,))": 3286,
      "(12, (1, 3, 8))": 316,
      "(12, (5, 7))": 10427,
      "(11, (2, 9))": 1364,
      "(11, (1, 3, 7))": 896,
      "(3, (1, 2))": 1249,
      "(12, (2, 4, 6))": 804,
      "(11, (2, 4, 5))": 1239,
      "(11, (1, 2, 8))": 14,
      "(12, (1, 2, 9))": 99
    },
    "4": {
      "(10, (2, 3, 5))": 49743,
      "(4, (4,))": 100385,
      "(10, (1, 9))": 108351,
      "(6, (6,))": 157002,
      "(7, (7,))": 224256,
      "(6, (2, 4))": 64292,
      "(11, (3, 8))": 31161,
      "(8, (1, 7))": 48170,
      "(5, (5,))": 104806,
      "(8, (2, 6))": 76956,
      "(10, (3, 7))": 39677,
      "(6, (1, 5))": 60232,
      "(8, (8,))": 250808,
      "(11, (2, 3, 6))": 32550,
      "(3, (3,))": 45487,
      "(9, (2, 7))": 9041,
      "(9, (9,))": 184027,
      "(11, (5, 6))": 20780,
      "(8, (3, 5))": 29590,
      "(7, (1, 6))": 54743,
      "(5, (2, 3))": 50581,
      "(1, (1,))": 5409,
      "(7, (2, 5))": 90620,
      "(9, (3, 6))": 30854,
      "(9, (4, 5))": 38494,
      "(7, (3, 4))": 37833,
      "(5, (1, 4))": 47618,
      "(9, (2, 3, 4))": 56269,
      "(12, (2, 3, 7))": 16969,
      "(9, (1, 8))": 30603,
      "(12, (1, 4, 7))": 2269,
      "(12, (4, 8))": 16788,
      "(11, (4, 7))": 26952,
      "(10, (4, 6))": 25269,
      "(4, (1, 3))": 16484,
      "(12, (5, 7))": 12269,
      "(2, (2,))": 11512,
      "(12, (3, 9))": 13934,
      "(11, (1, 4, 6))": 4314,
      "(11, (2, 9))": 1565,
      "(10, (2, 8))": 3807,
      "(12, (1, 5, 6))": 3505,
      "(12, (1, 3, 8))": 391,
      "(12, (3, 4, 5))": 2536,
      "(11, (2, 4, 5))": 1317,
      "(3, (1, 2))": 1265,
      "(11, (1, 3, 7))": 1114,
      "(12, (2, 4, 6))": 894,
      "(12, (1, 2, 9))": 128,
      "(11, (1, 2, 8))": 12
    }
  }
}